Metadata-Version: 2.1
Name: smart_open
Version: 7.0.5
Summary: Utils for streaming large files (S3, HDFS, GCS, Azure Blob Storage, gzip, bz2...)
Home-page: https://github.com/piskvorky/smart_open
Author: Radim Rehurek
Author-email: me@radimrehurek.com
Maintainer: Radim Rehurek
Maintainer-email: me@radimrehurek.com
License: MIT
Download-URL: http://pypi.python.org/pypi/smart_open
Keywords: file streaming,s3,hdfs,gcs,azure blob storage
Platform: any
Classifier: Development Status :: 5 - Production/Stable
Classifier: Environment :: Console
Classifier: Intended Audience :: Developers
Classifier: License :: OSI Approved :: MIT License
Classifier: Operating System :: OS Independent
Classifier: Programming Language :: Python :: 3.7
Classifier: Programming Language :: Python :: 3.8
Classifier: Programming Language :: Python :: 3.9
Classifier: Programming Language :: Python :: 3.10
Classifier: Programming Language :: Python :: 3.11
Classifier: Topic :: System :: Distributed Computing
Classifier: Topic :: Database :: Front-Ends
Requires-Python: >=3.7,<4.0
Provides-Extra: test
Provides-Extra: s3
Provides-Extra: gcs
Provides-Extra: azure
Provides-Extra: all
Provides-Extra: http
Provides-Extra: webhdfs
Provides-Extra: ssh
Provides-Extra: zst
